{
    "RootType": "saveMetadataContainer",
    "Data": {
        "metadata": {
            "gameDefinition": "",
            "activeQuests": "6B577A51814903CA",
            "trackedQuestEntry": "quests/main_quest/prologue/q003_maelstrom/maelstrom_deal/06_go_to_elevator2",
            "trackedQuest": "LocKey#9467",
            "mainQuest": "LocKey#9467",
            "debugString": "q003_entered_main_hall_allfoods",
            "locationName": "LocKey#44398",
            "playerPosition": {
                "X": -826.0822143554688,
                "Y": 2235.29931640625,
                "Z": 54.91575622558594
            },
            "playTime": 12684.3187878,
            "playthroughTime": 12866.8023198,
            "nextSavableEntityID": 9003795,
            "nextNonSavableEntityID": 10050957,
            "lifePath": "StreetKid",
            "bodyGender": "Male",
            "brainGender": "Male",
            "level": 6.0,
            "streetCred": 4.0,
            "gunslinger": 0.0,
            "assault": 1.0,
            "demolition": 1.0,
            "athletics": 1.0,
            "brawling": 1.0,
            "coldBlood": 1.0,
            "stealth": 1.0,
            "engineering": 1.0,
            "crafting": 1.0,
            "hacking": 1.0,
            "combatHacking": 1.0,
            "strength": 8.0,
            "intelligence": 4.0,
            "reflexes": 6.0,
            "technicalAbility": 6.0,
            "cool": 3.0,
            "initialBuildID": "3.0.5044915  P4CL: 6623767  Stream: R6.Release ",
            "finishedQuests": "q004 q000 q001 mq012 ma_wat_kab_08 ma_wat_nid_03 ma_wat_lch_14 ",
            "playthroughID": "66801d10fdced96d",
            "pointOfNoReturnId": "",
            "visitID": "9aa593ef-2ac3-4a4a-94a9-e82b59148a90",
            "buildSKU": "",
            "buildPatch": "2.12",
            "difficulty": "Easy",
            "facts": [
                "player_drunk=0",
                "q000_street_kid_background=1"
            ],
            "saveVersion": 263,
            "gameVersion": 2120,
            "timestampString": "14:35:44, 30.06.2024",
            "name": "AutoSave-11",
            "userName": "",
            "buildID": "3.0.5044915  P4CL: 6623767  Stream: R6.Release ",
            "platform": "pc",
            "censorFlags": "",
            "buildConfiguration": "final",
            "fileSize": 1859201,
            "isForced": true,
            "isCheckpoint": true,
            "initialLoadingScreenID": 186738114966,
            "isStoryMode": false,
            "isPointOfNoReturn": false,
            "isEndGameSave": false,
            "isModded": false,
            "additionalContentIds": []
        }
    }
}